funhub/__init__.py
funhub/cli.py
funhub/manager.py
funhub/base/__init__.py
funhub/base/config.py
funhub/base/provider.py
funhub/providers/__init__.py
funhub/providers/github.py
funhub/providers/huggingface.py
funhub-0.1.1.dist-info/METADATA
funhub-0.1.1.dist-info/WHEEL
funhub-0.1.1.dist-info/entry_points.txt
funhub-0.1.1.dist-info/licenses/LICENSE
funhub-0.1.1.dist-info/RECORD
