Metadata-Version: 2.4
Name: funhub
Version: 0.1.1
Summary: 统一管理GitHub、HuggingFace等Git仓库的代码存储工具
Project-URL: Organization, https://github.com/farfarfun
Project-URL: Repository, https://github.com/farfarfun/funhub
Project-URL: Releases, https://github.com/farfarfun/funhub/releases
Author-email: 牛哥 <niuliangtao@qq.com>, farfarfun <farfarfun@qq.com>
Maintainer-email: 牛哥 <niuliangtao@qq.com>, farfarfun <farfarfun@qq.com>
License-File: LICENSE
Requires-Python: >=3.12
Requires-Dist: click>=8.1.0
Requires-Dist: fundrive>=0.1.0
Requires-Dist: funutil>=0.1.0
Requires-Dist: gitpython>=3.1.0
Requires-Dist: pyyaml>=6.0
Requires-Dist: requests>=2.31.0
Requires-Dist: tqdm>=4.65.0
